{
  "config": [
    {
      "domain": "classin.xn--bgtt50a8xt.top",
      "name": "Cottie主站"
    },
    {
      "domain": "api.xn--bgtt50a8xt.top",
      "name": "CottieAPI网关"
    },
    {
      "domain": "blackblue.xn--bgtt50a8xt.top",
      "name": "黑洞节点"
    },
    {
      "domain": "cla.66ghz.com",
      "name": "[bird]小网站1"
    },
    {
      "domain": "rooma.mydiscussion.net",
      "name": "[bird]Classin千人群中转"
    },
    {
      "domain": "www.idcjk.com",
      "name": "[外部]IDC 风险以及信息查询系统"
    }
  ],
  "results": [
    {
      "domain": "classin.xn--bgtt50a8xt.top",
      "status_code": 200,
      "ok": true,
      "response_time_ms": 243,
      "checked_at": "2026-07-01T16:00:33.413154Z",
      "error": null
    },
    {
      "domain": "api.xn--bgtt50a8xt.top",
      "status_code": 200,
      "ok": true,
      "response_time_ms": 276,
      "checked_at": "2026-07-01T16:00:33.689140Z",
      "error": null
    },
    {
      "domain": "blackblue.xn--bgtt50a8xt.top",
      "status_code": 200,
      "ok": true,
      "response_time_ms": 228,
      "checked_at": "2026-07-01T16:00:33.917440Z",
      "error": null
    },
    {
      "domain": "cla.66ghz.com",
      "status_code": 200,
      "ok": true,
      "response_time_ms": 531,
      "checked_at": "2026-07-01T16:00:34.448156Z",
      "error": null
    },
    {
      "domain": "rooma.mydiscussion.net",
      "status_code": 200,
      "ok": true,
      "response_time_ms": 523,
      "checked_at": "2026-07-01T16:00:34.971436Z",
      "error": null
    },
    {
      "domain": "www.idcjk.com",
      "status_code": 200,
      "ok": true,
      "response_time_ms": 229,
      "checked_at": "2026-07-01T16:00:35.200087Z",
      "error": null
    }
  ],
  "updated_at": "2026-07-01T16:00:35.200104Z"
}