{
  "config": [
    {
      "domain": "classin.xn--bgtt50a8xt.top",
      "name": "Cottie主站"
    },
    {
      "domain": "api.xn--bgtt50a8xt.top",
      "name": "CottieAPI网关"
    },
    {
      "domain": "blackblue.xn--bgtt50a8xt.top",
      "name": "黑洞节点"
    },
    {
      "domain": "cla.66ghz.com",
      "name": "[bird]小网站1"
    },
    {
      "domain": "rooma.mydiscussion.net",
      "name": "[bird]Classin千人群中转"
    },
    {
      "domain": "www.idcjk.com",
      "name": "[外部]IDC 风险以及信息查询系统"
    }
  ],
  "results": [
    {
      "domain": "classin.xn--bgtt50a8xt.top",
      "status_code": 200,
      "ok": true,
      "response_time_ms": 115,
      "checked_at": "2026-05-27T05:00:23.758618Z",
      "error": null
    },
    {
      "domain": "api.xn--bgtt50a8xt.top",
      "status_code": 200,
      "ok": true,
      "response_time_ms": 1018,
      "checked_at": "2026-05-27T05:00:24.776153Z",
      "error": null
    },
    {
      "domain": "blackblue.xn--bgtt50a8xt.top",
      "status_code": 200,
      "ok": true,
      "response_time_ms": 128,
      "checked_at": "2026-05-27T05:00:24.904454Z",
      "error": null
    },
    {
      "domain": "cla.66ghz.com",
      "status_code": 200,
      "ok": true,
      "response_time_ms": 1038,
      "checked_at": "2026-05-27T05:00:25.942671Z",
      "error": null
    },
    {
      "domain": "rooma.mydiscussion.net",
      "status_code": 200,
      "ok": true,
      "response_time_ms": 569,
      "checked_at": "2026-05-27T05:00:26.511919Z",
      "error": null
    },
    {
      "domain": "www.idcjk.com",
      "status_code": 200,
      "ok": true,
      "response_time_ms": 1043,
      "checked_at": "2026-05-27T05:00:27.555146Z",
      "error": null
    }
  ],
  "updated_at": "2026-05-27T05:00:27.555164Z"
}