{
  "config": [
    {
      "domain": "classin.xn--bgtt50a8xt.top",
      "name": "Cottie主站"
    },
    {
      "domain": "api.xn--bgtt50a8xt.top",
      "name": "CottieAPI网关"
    },
    {
      "domain": "blackblue.xn--bgtt50a8xt.top",
      "name": "黑洞节点"
    },
    {
      "domain": "cla.66ghz.com",
      "name": "[bird]小网站1"
    },
    {
      "domain": "c0.ct.ws",
      "name": "[bird]小网站2（备用)"
    },
    {
      "domain": "www.idcjk.com",
      "name": "[外部]IDC 风险以及信息查询系统"
    }
  ],
  "results": [
    {
      "domain": "classin.xn--bgtt50a8xt.top",
      "status_code": 200,
      "ok": true,
      "response_time_ms": 268,
      "checked_at": "2026-05-15T05:00:25.240276Z",
      "error": null
    },
    {
      "domain": "api.xn--bgtt50a8xt.top",
      "status_code": null,
      "ok": false,
      "response_time_ms": 155,
      "checked_at": "2026-05-15T05:00:25.394998Z",
      "error": "NoRedirectHandler.redirect_request() missing 1 required positional argument: 'newurl'"
    },
    {
      "domain": "blackblue.xn--bgtt50a8xt.top",
      "status_code": 200,
      "ok": true,
      "response_time_ms": 212,
      "checked_at": "2026-05-15T05:00:25.606580Z",
      "error": null
    },
    {
      "domain": "cla.66ghz.com",
      "status_code": 200,
      "ok": true,
      "response_time_ms": 575,
      "checked_at": "2026-05-15T05:00:26.182053Z",
      "error": null
    },
    {
      "domain": "c0.ct.ws",
      "status_code": 200,
      "ok": true,
      "response_time_ms": 532,
      "checked_at": "2026-05-15T05:00:26.714246Z",
      "error": null
    },
    {
      "domain": "www.idcjk.com",
      "status_code": 200,
      "ok": true,
      "response_time_ms": 981,
      "checked_at": "2026-05-15T05:00:27.695645Z",
      "error": null
    }
  ],
  "updated_at": "2026-05-15T05:00:27.695660Z"
}