{
  "config": [
    {
      "domain": "classin.xn--bgtt50a8xt.top",
      "name": "Cottie主站"
    },
    {
      "domain": "api.xn--bgtt50a8xt.top",
      "name": "CottieAPI网关"
    },
    {
      "domain": "blackblue.xn--bgtt50a8xt.top",
      "name": "黑洞节点"
    },
    {
      "domain": "cla.66ghz.com",
      "name": "[bird]小网站1"
    },
    {
      "domain": "c0.ct.ws",
      "name": "[bird]小网站2（备用)"
    },
    {
      "domain": "www.idcjk.com",
      "name": "[外部]IDC 风险以及信息查询系统"
    }
  ],
  "results": [
    {
      "domain": "classin.xn--bgtt50a8xt.top",
      "status_code": 200,
      "ok": true,
      "response_time_ms": 135,
      "checked_at": "2026-05-21T23:00:24.053333Z",
      "error": null
    },
    {
      "domain": "api.xn--bgtt50a8xt.top",
      "status_code": 200,
      "ok": true,
      "response_time_ms": 920,
      "checked_at": "2026-05-21T23:00:24.972939Z",
      "error": null
    },
    {
      "domain": "blackblue.xn--bgtt50a8xt.top",
      "status_code": 200,
      "ok": true,
      "response_time_ms": 448,
      "checked_at": "2026-05-21T23:00:25.420933Z",
      "error": null
    },
    {
      "domain": "cla.66ghz.com",
      "status_code": 200,
      "ok": true,
      "response_time_ms": 526,
      "checked_at": "2026-05-21T23:00:25.946917Z",
      "error": null
    },
    {
      "domain": "c0.ct.ws",
      "status_code": null,
      "ok": false,
      "response_time_ms": 822,
      "checked_at": "2026-05-21T23:00:26.769244Z",
      "error": "<urlopen error [Errno -3] Temporary failure in name resolution>"
    },
    {
      "domain": "www.idcjk.com",
      "status_code": 200,
      "ok": true,
      "response_time_ms": 1020,
      "checked_at": "2026-05-21T23:00:27.789244Z",
      "error": null
    }
  ],
  "updated_at": "2026-05-21T23:00:27.789262Z"
}